qtl_instrument_book/__init__.py
qtl_instrument_book/data/futures.toml
qtl_instrument_book/data/options.toml
qtl_instrument_book-20220121.dist-info/METADATA
qtl_instrument_book-20220121.dist-info/WHEEL
qtl_instrument_book-20220121.dist-info/top_level.txt
qtl_instrument_book-20220121.dist-info/RECORD
