Metadata-Version: 2.1
Name: qtl-instrument-book
Version: 20220121
Summary: Quantalon Instrument Book
Home-page: UNKNOWN
License: UNKNOWN
Platform: UNKNOWN
Requires-Python: >=3.9.0
Requires-Dist: toml
